drf_link_navigation_pagination/__init__.py
drf_link_navigation_pagination/exceptions.py
drf_link_navigation_pagination-1.0.2.dist-info/licenses/LICENSE
tests/__init__.py
tests/conftest.py
tests/integration/__init__.py
tests/integration/test_init.py
tests/support/__init__.py
tests/support/fake_django_app/__init__.py
tests/support/fake_django_app/models.py
tests/support/fake_django_app/urls.py
tests/support/fake_django_app/views.py
drf_link_navigation_pagination-1.0.2.dist-info/METADATA
drf_link_navigation_pagination-1.0.2.dist-info/WHEEL
drf_link_navigation_pagination-1.0.2.dist-info/top_level.txt
drf_link_navigation_pagination-1.0.2.dist-info/RECORD
