Metadata-Version: 2.4
Name: drf-link-navigation-pagination
Version: 1.0.2
Summary: Yet another pagination class for DRF to set host address by header
Home-page: https://github.com/juntossomosmais/drf-link-navigation-pagination
Author: Willian Antunes
Author-email: Willian Antunes <willian.lima.antunes@gmail.com>
License: MIT
Classifier: Programming Language :: Python :: 3.12
Classifier: Framework :: Django :: 5.2
Classifier: Environment :: Web Environment
Classifier: Intended Audience :: Developers
Classifier: License :: OSI Approved :: MIT License
Classifier: Operating System :: OS Independent
License-File: LICENSE
Requires-Dist: django
Requires-Dist: djangorestframework
Dynamic: author
Dynamic: author-email
Dynamic: classifier
Dynamic: description
Dynamic: description-content-type
Dynamic: home-page
Dynamic: license
Dynamic: license-file
Dynamic: requires-dist
Dynamic: summary
